PowerQuant/__init__.py
PowerQuant/core.py
PowerQuant-0.1.0.dist-info/LICENSE
PowerQuant-0.1.0.dist-info/METADATA
PowerQuant-0.1.0.dist-info/WHEEL
PowerQuant-0.1.0.dist-info/top_level.txt
PowerQuant-0.1.0.dist-info/RECORD
