Metadata-Version: 2.1
Name: PowerQuant
Version: 0.1.0
Summary: Quantitative analysis for power markets
Author: Jean Bertin
Author-email: <jeanbertin.ensam@gmail.com>
Keywords: python,quantitative,risk,power,quant
Classifier: Development Status :: 1 - Planning
Classifier: Intended Audience :: Developers
Classifier: Programming Language :: Python :: 3
Classifier: Operating System :: Unix
Classifier: Operating System :: MacOS :: MacOS X
Classifier: Operating System :: Microsoft :: Windows
License-File: LICENSE
Requires-Dist: pandas
Requires-Dist: numpy
